spaken/__init__.py
spaken/cmd.py
spaken/exceptions.py
spaken/finder.py
spaken/helpers.py
spaken/s3.py
spaken-0.2.1.dist-info/LICENSE
spaken-0.2.1.dist-info/METADATA
spaken-0.2.1.dist-info/WHEEL
spaken-0.2.1.dist-info/entry_points.txt
spaken-0.2.1.dist-info/top_level.txt
spaken-0.2.1.dist-info/RECORD
